sequence_align-0.3.0.dist-info/METADATA
sequence_align-0.3.0.dist-info/WHEEL
sequence_align-0.3.0.dist-info/licenses/LICENSE
sequence_align-0.3.0.dist-info/licenses/AUTHORS.md
sequence_align/pairwise.py
sequence_align/py.typed
sequence_align/__init__.py
sequence_align/_sequence_align.abi3.so
sequence_align-0.3.0.dist-info/RECORD
