Metadata-Version: 2.4
Name: sequence_align
Version: 0.3.0
Classifier: Operating System :: OS Independent
Classifier: Programming Language :: Python :: 3.9
Classifier: Programming Language :: Python :: 3.10
Classifier: Programming Language :: Python :: 3.11
Classifier: Programming Language :: Python :: 3.12
Classifier: Programming Language :: Python :: 3.13
Classifier: Programming Language :: Rust
Classifier: Topic :: Scientific/Engineering :: Artificial Intelligence
Classifier: Topic :: Scientific/Engineering :: Bio-Informatics
Classifier: Typing :: Typed
Requires-Dist: bandit ; extra == 'dev'
Requires-Dist: black ; extra == 'dev'
Requires-Dist: flake8 ; extra == 'dev'
Requires-Dist: isort>=5.0.0,<6 ; extra == 'dev'
Requires-Dist: mypy ; extra == 'dev'
Requires-Dist: psutil ; extra == 'dev'
Requires-Dist: pydocstyle ; extra == 'dev'
Requires-Dist: pylint ; extra == 'dev'
Requires-Dist: pytest ; extra == 'dev'
Requires-Dist: pytest-cov ; extra == 'dev'
Requires-Dist: pytest-subtests ; extra == 'dev'
Requires-Dist: pyyaml ; extra == 'dev'
Requires-Dist: types-psutil ; extra == 'dev'
Requires-Dist: types-pyyaml ; extra == 'dev'
Provides-Extra: dev
License-File: LICENSE
License-File: AUTHORS.md
Summary: Efficient implementations of Needleman-Wunsch and other sequence alignment algorithms in Rust with Python bindings.
Author-email: "Kensho Technologies LLC." <sequence-align-maintainer@kensho.com>
Maintainer-email: "Kensho Technologies LLC." <sequence-align-maintainer@kensho.com>
License: Apache-2.0
Requires-Python: >=3.9, <3.14
Project-URL: source, https://github.com/kensho-technologies/sequence_align
Project-URL: Homepage, https://github.com/kensho-technologies/sequence_align
Project-URL: Bug Tracker, https://github.com/kensho-technologies/sequence_align/issues
